GA_HW/__init__.py
ga_hw-0.0.1.dist-info/METADATA
ga_hw-0.0.1.dist-info/WHEEL
ga_hw-0.0.1.dist-info/licenses/LICENSE.txt
ga_hw-0.0.1.dist-info/RECORD
