Metadata-Version: 2.4
Name: GA_HW
Version: 0.0.1
Project-URL: Homepage, https://github.com/JorgePiquerasMarques
Project-URL: Orcid, https://orcid.org/0000-0002-6812-2106
Author-email: Jorge Piqueras-Marqués <floydpik@gmail.com>
License-File: LICENSE.txt
Requires-Python: >=3.0
